{
  "openapi": "3.0.1",
  "info": {
    "title": "HealthyCareAssistant API",
    "description": "API documentation for HealthyCareAssistant",
    "version": "v1"
  },
  "paths": {
    "/api/auth/register": {
      "post": {
        "tags": [
          "auth"
        ],
        "requestBody": {
          "content": {
            "application/json": {
              "schema": {
                "$ref": "#/components/schemas/RegisterModelViews"
              }
            },
            "text/json": {
              "schema": {
                "$ref": "#/components/schemas/RegisterModelViews"
              }
            },
            "application/*+json": {
              "schema": {
                "$ref": "#/components/schemas/RegisterModelViews"
              }
            }
          }
        },
        "responses": {
          "200": {
            "description": "OK"
          }
        }
      }
    },
    "/api/auth/login": {
      "post": {
        "tags": [
          "auth"
        ],
        "requestBody": {
          "content": {
            "application/json": {
              "schema": {
                "$ref": "#/components/schemas/LoginModelViews"
              }
            },
            "text/json": {
              "schema": {
                "$ref": "#/components/schemas/LoginModelViews"
              }
            },
            "application/*+json": {
              "schema": {
                "$ref": "#/components/schemas/LoginModelViews"
              }
            }
          }
        },
        "responses": {
          "200": {
            "description": "OK"
          }
        }
      }
    },
    "/api/auth/google-login": {
      "post": {
        "tags": [
          "auth"
        ],
        "requestBody": {
          "content": {
            "application/json": {
              "schema": {
                "$ref": "#/components/schemas/TokenRqGoogleLogin"
              }
            },
            "text/json": {
              "schema": {
                "$ref": "#/components/schemas/TokenRqGoogleLogin"
              }
            },
            "application/*+json": {
              "schema": {
                "$ref": "#/components/schemas/TokenRqGoogleLogin"
              }
            }
          }
        },
        "responses": {
          "200": {
            "description": "OK"
          }
        }
      }
    },
    "/api/auth/generate-token": {
      "post": {
        "tags": [
          "auth"
        ],
        "requestBody": {
          "content": {
            "application/json": {
              "schema": {
                "$ref": "#/components/schemas/LoginRequest"
              }
            },
            "text/json": {
              "schema": {
                "$ref": "#/components/schemas/LoginRequest"
              }
            },
            "application/*+json": {
              "schema": {
                "$ref": "#/components/schemas/LoginRequest"
              }
            }
          }
        },
        "responses": {
          "200": {
            "description": "OK"
          }
        }
      }
    },
    "/api/auth/refresh-token": {
      "post": {
        "tags": [
          "auth"
        ],
        "requestBody": {
          "content": {
            "application/json": {
              "schema": {
                "$ref": "#/components/schemas/TokenRequest"
              }
            },
            "text/json": {
              "schema": {
                "$ref": "#/components/schemas/TokenRequest"
              }
            },
            "application/*+json": {
              "schema": {
                "$ref": "#/components/schemas/TokenRequest"
              }
            }
          }
        },
        "responses": {
          "200": {
            "description": "OK"
          }
        }
      }
    },
    "/api/auth/forgot-password": {
      "post": {
        "tags": [
          "auth"
        ],
        "requestBody": {
          "content": {
            "application/json": {
              "schema": {
                "$ref": "#/components/schemas/ForgotPasswordModel"
              }
            },
            "text/json": {
              "schema": {
                "$ref": "#/components/schemas/ForgotPasswordModel"
              }
            },
            "application/*+json": {
              "schema": {
                "$ref": "#/components/schemas/ForgotPasswordModel"
              }
            }
          }
        },
        "responses": {
          "200": {
            "description": "OK"
          }
        }
      }
    },
    "/api/auth/reset-password": {
      "post": {
        "tags": [
          "auth"
        ],
        "requestBody": {
          "content": {
            "application/json": {
              "schema": {
                "$ref": "#/components/schemas/ResetPasswordModel"
              }
            },
            "text/json": {
              "schema": {
                "$ref": "#/components/schemas/ResetPasswordModel"
              }
            },
            "application/*+json": {
              "schema": {
                "$ref": "#/components/schemas/ResetPasswordModel"
              }
            }
          }
        },
        "responses": {
          "200": {
            "description": "OK"
          }
        }
      }
    },
    "/api/auth/me": {
      "get": {
        "tags": [
          "auth"
        ],
        "responses": {
          "200": {
            "description": "OK"
          }
        }
      }
    },
    "/api/drugs": {
      "get": {
        "tags": [
          "Drug"
        ],
        "parameters": [
          {
            "name": "page",
            "in": "query",
            "schema": {
              "type": "integer",
              "format": "int32",
              "default": 1
            }
          },
          {
            "name": "pageSize",
            "in": "query",
            "schema": {
              "type": "integer",
              "format": "int32",
              "default": 20
            }
          }
        ],
        "responses": {
          "200": {
            "description": "OK"
          }
        }
      },
      "post": {
        "tags": [
          "Drug"
        ],
        "requestBody": {
          "content": {
            "application/json": {
              "schema": {
                "$ref": "#/components/schemas/DrugModelView"
              }
            },
            "text/json": {
              "schema": {
                "$ref": "#/components/schemas/DrugModelView"
              }
            },
            "application/*+json": {
              "schema": {
                "$ref": "#/components/schemas/DrugModelView"
              }
            }
          }
        },
        "responses": {
          "200": {
            "description": "OK"
          }
        }
      }
    },
    "/api/drugs/{id}": {
      "get": {
        "tags": [
          "Drug"
        ],
        "parameters": [
          {
            "name": "id",
            "in": "path",
            "required": true,
            "schema": {
              "type": "string"
            }
          }
        ],
        "responses": {
          "200": {
            "description": "OK"
          }
        }
      },
      "delete": {
        "tags": [
          "Drug"
        ],
        "parameters": [
          {
            "name": "id",
            "in": "path",
            "required": true,
            "schema": {
              "type": "string"
            }
          }
        ],
        "responses": {
          "200": {
            "description": "OK"
          }
        }
      },
      "put": {
        "tags": [
          "Drug"
        ],
        "parameters": [
          {
            "name": "id",
            "in": "path",
            "required": true,
            "schema": {
              "type": "string"
            }
          }
        ],
        "requestBody": {
          "content": {
            "application/json": {
              "schema": {
                "$ref": "#/components/schemas/UpdateDrugModelView"
              }
            },
            "text/json": {
              "schema": {
                "$ref": "#/components/schemas/UpdateDrugModelView"
              }
            },
            "application/*+json": {
              "schema": {
                "$ref": "#/components/schemas/UpdateDrugModelView"
              }
            }
          }
        },
        "responses": {
          "200": {
            "description": "OK"
          }
        }
      }
    },
    "/api/drugs/search/name": {
      "get": {
        "tags": [
          "Drug"
        ],
        "parameters": [
          {
            "name": "name",
            "in": "query",
            "schema": {
              "type": "string"
            }
          }
        ],
        "responses": {
          "200": {
            "description": "OK"
          }
        }
      }
    },
    "/api/drugs/search/ingredient": {
      "get": {
        "tags": [
          "Drug"
        ],
        "parameters": [
          {
            "name": "ingredient",
            "in": "query",
            "schema": {
              "type": "string"
            }
          }
        ],
        "responses": {
          "200": {
            "description": "OK"
          }
        }
      }
    },
    "/api/drugs/filter/company": {
      "get": {
        "tags": [
          "Drug"
        ],
        "parameters": [
          {
            "name": "companyName",
            "in": "query",
            "schema": {
              "type": "string"
            }
          }
        ],
        "responses": {
          "200": {
            "description": "OK"
          }
        }
      }
    },
    "/api/drugs/filter/category": {
      "get": {
        "tags": [
          "Drug"
        ],
        "parameters": [
          {
            "name": "category",
            "in": "query",
            "schema": {
              "type": "string"
            }
          },
          {
            "name": "page",
            "in": "query",
            "schema": {
              "type": "integer",
              "format": "int32",
              "default": 1
            }
          },
          {
            "name": "pageSize",
            "in": "query",
            "schema": {
              "type": "integer",
              "format": "int32",
              "default": 20
            }
          }
        ],
        "responses": {
          "200": {
            "description": "OK"
          }
        }
      }
    },
    "/api/drugs/related/ingredient/{id}": {
      "get": {
        "tags": [
          "Drug"
        ],
        "parameters": [
          {
            "name": "id",
            "in": "path",
            "required": true,
            "schema": {
              "type": "string"
            }
          }
        ],
        "responses": {
          "200": {
            "description": "OK"
          }
        }
      }
    },
    "/api/drugs/related/company": {
      "get": {
        "tags": [
          "Drug"
        ],
        "parameters": [
          {
            "name": "id",
            "in": "query",
            "schema": {
              "type": "string"
            }
          }
        ],
        "responses": {
          "200": {
            "description": "OK"
          }
        }
      }
    },
    "/api/drugs/top-searched": {
      "get": {
        "tags": [
          "Drug"
        ],
        "responses": {
          "200": {
            "description": "OK"
          }
        }
      }
    },
    "/api/drugs/top-new-registered": {
      "get": {
        "tags": [
          "Drug"
        ],
        "responses": {
          "200": {
            "description": "OK"
          }
        }
      }
    },
    "/api/drugs/top-withdrawn": {
      "get": {
        "tags": [
          "Drug"
        ],
        "responses": {
          "200": {
            "description": "OK"
          }
        }
      }
    },
    "/api/drugs/top-companies": {
      "get": {
        "tags": [
          "Drug"
        ],
        "responses": {
          "200": {
            "description": "OK"
          }
        }
      }
    },
    "/api/drugs/{drugId}/image/upload": {
      "post": {
        "tags": [
          "Drug"
        ],
        "parameters": [
          {
            "name": "drugId",
            "in": "path",
            "required": true,
            "schema": {
              "type": "string"
            }
          }
        ],
        "requestBody": {
          "content": {
            "multipart/form-data": {
              "schema": {
                "type": "object",
                "properties": {
                  "File": {
                    "type": "string",
                    "format": "binary"
                  }
                }
              },
              "encoding": {
                "File": {
                  "style": "form"
                }
              }
            }
          }
        },
        "responses": {
          "200": {
            "description": "OK"
          }
        }
      }
    },
    "/api/drugs/{drugId}/image/{fileName}": {
      "get": {
        "tags": [
          "Drug"
        ],
        "parameters": [
          {
            "name": "drugId",
            "in": "path",
            "required": true,
            "schema": {
              "type": "string"
            }
          },
          {
            "name": "fileName",
            "in": "path",
            "required": true,
            "schema": {
              "type": "string"
            }
          }
        ],
        "responses": {
          "200": {
            "description": "OK"
          }
        }
      },
      "delete": {
        "tags": [
          "Drug"
        ],
        "parameters": [
          {
            "name": "drugId",
            "in": "path",
            "required": true,
            "schema": {
              "type": "string"
            }
          },
          {
            "name": "fileName",
            "in": "path",
            "required": true,
            "schema": {
              "type": "string"
            }
          }
        ],
        "responses": {
          "200": {
            "description": "OK"
          }
        }
      }
    },
    "/api/drugs/{drugId}/image/uploads": {
      "post": {
        "tags": [
          "Drug"
        ],
        "parameters": [
          {
            "name": "drugId",
            "in": "path",
            "required": true,
            "schema": {
              "type": "string"
            }
          }
        ],
        "requestBody": {
          "content": {
            "multipart/form-data": {
              "schema": {
                "type": "object",
                "properties": {
                  "files": {
                    "type": "array",
                    "items": {
                      "type": "string",
                      "format": "binary"
                    }
                  }
                }
              },
              "encoding": {
                "files": {
                  "style": "form"
                }
              }
            }
          }
        },
        "responses": {
          "200": {
            "description": "OK"
          }
        }
      }
    },
    "/api/drugs/{drugId}/pdf/upload": {
      "post": {
        "tags": [
          "Drug"
        ],
        "parameters": [
          {
            "name": "drugId",
            "in": "path",
            "required": true,
            "schema": {
              "type": "string"
            }
          }
        ],
        "requestBody": {
          "content": {
            "multipart/form-data": {
              "schema": {
                "type": "object",
                "properties": {
                  "file": {
                    "type": "string",
                    "format": "binary"
                  }
                }
              },
              "encoding": {
                "file": {
                  "style": "form"
                }
              }
            }
          }
        },
        "responses": {
          "200": {
            "description": "OK"
          }
        }
      }
    },
    "/api/drugs/{drugId}/pdf/{fileName}": {
      "get": {
        "tags": [
          "Drug"
        ],
        "parameters": [
          {
            "name": "drugId",
            "in": "path",
            "required": true,
            "schema": {
              "type": "string"
            }
          },
          {
            "name": "fileName",
            "in": "path",
            "required": true,
            "schema": {
              "type": "string"
            }
          }
        ],
        "responses": {
          "200": {
            "description": "OK"
          }
        }
      },
      "delete": {
        "tags": [
          "Drug"
        ],
        "parameters": [
          {
            "name": "drugId",
            "in": "path",
            "required": true,
            "schema": {
              "type": "string"
            }
          },
          {
            "name": "fileName",
            "in": "path",
            "required": true,
            "schema": {
              "type": "string"
            }
          }
        ],
        "responses": {
          "200": {
            "description": "OK"
          }
        }
      }
    },
    "/api/medicine-cabinet/create-empty": {
      "post": {
        "tags": [
          "MedicineCabinet"
        ],
        "parameters": [
          {
            "name": "userId",
            "in": "query",
            "schema": {
              "type": "integer",
              "format": "int32"
            }
          },
          {
            "name": "cabinetName",
            "in": "query",
            "schema": {
              "type": "string"
            }
          },
          {
            "name": "description",
            "in": "query",
            "schema": {
              "type": "string"
            }
          }
        ],
        "responses": {
          "200": {
            "description": "OK"
          }
        }
      }
    },
    "/api/medicine-cabinet/create": {
      "post": {
        "tags": [
          "MedicineCabinet"
        ],
        "parameters": [
          {
            "name": "userId",
            "in": "query",
            "schema": {
              "type": "integer",
              "format": "int32"
            }
          }
        ],
        "requestBody": {
          "content": {
            "application/json": {
              "schema": {
                "$ref": "#/components/schemas/CreateCabinetWithDrugsRequest"
              }
            },
            "text/json": {
              "schema": {
                "$ref": "#/components/schemas/CreateCabinetWithDrugsRequest"
              }
            },
            "application/*+json": {
              "schema": {
                "$ref": "#/components/schemas/CreateCabinetWithDrugsRequest"
              }
            }
          }
        },
        "responses": {
          "200": {
            "description": "OK"
          }
        }
      }
    },
    "/api/medicine-cabinet/user/{userId}": {
      "get": {
        "tags": [
          "MedicineCabinet"
        ],
        "parameters": [
          {
            "name": "userId",
            "in": "path",
            "required": true,
            "schema": {
              "type": "integer",
              "format": "int32"
            }
          }
        ],
        "responses": {
          "200": {
            "description": "OK"
          }
        }
      }
    },
    "/api/medicine-cabinet/{cabinetId}": {
      "put": {
        "tags": [
          "MedicineCabinet"
        ],
        "parameters": [
          {
            "name": "cabinetId",
            "in": "path",
            "required": true,
            "schema": {
              "type": "integer",
              "format": "int32"
            }
          },
          {
            "name": "cabinetName",
            "in": "query",
            "schema": {
              "type": "string"
            }
          },
          {
            "name": "description",
            "in": "query",
            "schema": {
              "type": "string"
            }
          }
        ],
        "responses": {
          "200": {
            "description": "OK"
          }
        }
      },
      "delete": {
        "tags": [
          "MedicineCabinet"
        ],
        "parameters": [
          {
            "name": "cabinetId",
            "in": "path",
            "required": true,
            "schema": {
              "type": "integer",
              "format": "int32"
            }
          }
        ],
        "responses": {
          "200": {
            "description": "OK"
          }
        }
      }
    },
    "/api/medicine-cabinet/{cabinetId}/update-drugs": {
      "put": {
        "tags": [
          "MedicineCabinet"
        ],
        "parameters": [
          {
            "name": "cabinetId",
            "in": "path",
            "required": true,
            "schema": {
              "type": "integer",
              "format": "int32"
            }
          }
        ],
        "requestBody": {
          "content": {
            "application/json": {
              "schema": {
                "type": "array",
                "items": {
                  "type": "string"
                }
              }
            },
            "text/json": {
              "schema": {
                "type": "array",
                "items": {
                  "type": "string"
                }
              }
            },
            "application/*+json": {
              "schema": {
                "type": "array",
                "items": {
                  "type": "string"
                }
              }
            }
          }
        },
        "responses": {
          "200": {
            "description": "OK"
          }
        }
      }
    },
    "/api/medicine-cabinet/{cabinetId}/drugs": {
      "get": {
        "tags": [
          "MedicineCabinet"
        ],
        "parameters": [
          {
            "name": "cabinetId",
            "in": "path",
            "required": true,
            "schema": {
              "type": "integer",
              "format": "int32"
            }
          }
        ],
        "responses": {
          "200": {
            "description": "OK"
          }
        }
      }
    },
    "/api/reminders/user/{userId}": {
      "get": {
        "tags": [
          "Reminder"
        ],
        "parameters": [
          {
            "name": "userId",
            "in": "path",
            "required": true,
            "schema": {
              "type": "integer",
              "format": "int32"
            }
          }
        ],
        "responses": {
          "200": {
            "description": "OK"
          }
        }
      }
    },
    "/api/reminders/create": {
      "post": {
        "tags": [
          "Reminder"
        ],
        "parameters": [
          {
            "name": "userId",
            "in": "query",
            "schema": {
              "type": "integer",
              "format": "int32"
            }
          }
        ],
        "requestBody": {
          "content": {
            "application/json": {
              "schema": {
                "$ref": "#/components/schemas/CreateReminderRequest"
              }
            },
            "text/json": {
              "schema": {
                "$ref": "#/components/schemas/CreateReminderRequest"
              }
            },
            "application/*+json": {
              "schema": {
                "$ref": "#/components/schemas/CreateReminderRequest"
              }
            }
          }
        },
        "responses": {
          "200": {
            "description": "OK"
          }
        }
      }
    },
    "/api/reminders/{reminderId}": {
      "get": {
        "tags": [
          "Reminder"
        ],
        "parameters": [
          {
            "name": "reminderId",
            "in": "path",
            "required": true,
            "schema": {
              "type": "integer",
              "format": "int32"
            }
          }
        ],
        "responses": {
          "200": {
            "description": "OK"
          }
        }
      },
      "delete": {
        "tags": [
          "Reminder"
        ],
        "parameters": [
          {
            "name": "reminderId",
            "in": "path",
            "required": true,
            "schema": {
              "type": "integer",
              "format": "int32"
            }
          }
        ],
        "responses": {
          "200": {
            "description": "OK"
          }
        }
      },
      "put": {
        "tags": [
          "Reminder"
        ],
        "parameters": [
          {
            "name": "reminderId",
            "in": "path",
            "required": true,
            "schema": {
              "type": "integer",
              "format": "int32"
            }
          }
        ],
        "requestBody": {
          "content": {
            "application/json": {
              "schema": {
                "$ref": "#/components/schemas/UpdateReminderRequest"
              }
            },
            "text/json": {
              "schema": {
                "$ref": "#/components/schemas/UpdateReminderRequest"
              }
            },
            "application/*+json": {
              "schema": {
                "$ref": "#/components/schemas/UpdateReminderRequest"
              }
            }
          }
        },
        "responses": {
          "200": {
            "description": "OK"
          }
        }
      }
    },
    "/api/reminders/{reminderId}/toggle-status": {
      "put": {
        "tags": [
          "Reminder"
        ],
        "parameters": [
          {
            "name": "reminderId",
            "in": "path",
            "required": true,
            "schema": {
              "type": "integer",
              "format": "int32"
            }
          }
        ],
        "responses": {
          "200": {
            "description": "OK"
          }
        }
      }
    },
    "/api/users": {
      "get": {
        "tags": [
          "User"
        ],
        "parameters": [
          {
            "name": "page",
            "in": "query",
            "schema": {
              "type": "integer",
              "format": "int32",
              "default": 1
            }
          },
          {
            "name": "pageSize",
            "in": "query",
            "schema": {
              "type": "integer",
              "format": "int32",
              "default": 20
            }
          }
        ],
        "responses": {
          "200": {
            "description": "OK"
          }
        }
      },
      "post": {
        "tags": [
          "User"
        ],
        "requestBody": {
          "content": {
            "application/json": {
              "schema": {
                "$ref": "#/components/schemas/UserCreateRequest"
              }
            },
            "text/json": {
              "schema": {
                "$ref": "#/components/schemas/UserCreateRequest"
              }
            },
            "application/*+json": {
              "schema": {
                "$ref": "#/components/schemas/UserCreateRequest"
              }
            }
          }
        },
        "responses": {
          "200": {
            "description": "OK"
          }
        }
      }
    },
    "/api/users/{userId}": {
      "get": {
        "tags": [
          "User"
        ],
        "parameters": [
          {
            "name": "userId",
            "in": "path",
            "required": true,
            "schema": {
              "type": "integer",
              "format": "int32"
            }
          }
        ],
        "responses": {
          "200": {
            "description": "OK"
          }
        }
      },
      "put": {
        "tags": [
          "User"
        ],
        "parameters": [
          {
            "name": "userId",
            "in": "path",
            "required": true,
            "schema": {
              "type": "integer",
              "format": "int32"
            }
          }
        ],
        "requestBody": {
          "content": {
            "application/json": {
              "schema": {
                "$ref": "#/components/schemas/UserUpdateRequest"
              }
            },
            "text/json": {
              "schema": {
                "$ref": "#/components/schemas/UserUpdateRequest"
              }
            },
            "application/*+json": {
              "schema": {
                "$ref": "#/components/schemas/UserUpdateRequest"
              }
            }
          }
        },
        "responses": {
          "200": {
            "description": "OK"
          }
        }
      },
      "delete": {
        "tags": [
          "User"
        ],
        "parameters": [
          {
            "name": "userId",
            "in": "path",
            "required": true,
            "schema": {
              "type": "integer",
              "format": "int32"
            }
          }
        ],
        "responses": {
          "200": {
            "description": "OK"
          }
        }
      }
    },
    "/api/users/search": {
      "get": {
        "tags": [
          "User"
        ],
        "parameters": [
          {
            "name": "keyword",
            "in": "query",
            "schema": {
              "type": "string"
            }
          }
        ],
        "responses": {
          "200": {
            "description": "OK"
          }
        }
      }
    },
    "/api/users/{userid}/image/upload": {
      "post": {
        "tags": [
          "User"
        ],
        "parameters": [
          {
            "name": "userid",
            "in": "path",
            "required": true,
            "schema": {
              "type": "string"
            }
          }
        ],
        "requestBody": {
          "content": {
            "multipart/form-data": {
              "schema": {
                "type": "object",
                "properties": {
                  "File": {
                    "type": "string",
                    "format": "binary"
                  }
                }
              },
              "encoding": {
                "File": {
                  "style": "form"
                }
              }
            }
          }
        },
        "responses": {
          "200": {
            "description": "OK"
          }
        }
      }
    },
    "/api/users/{userid}/image/{fileName}": {
      "get": {
        "tags": [
          "User"
        ],
        "parameters": [
          {
            "name": "userid",
            "in": "path",
            "required": true,
            "schema": {
              "type": "string"
            }
          },
          {
            "name": "fileName",
            "in": "path",
            "required": true,
            "schema": {
              "type": "string"
            }
          }
        ],
        "responses": {
          "200": {
            "description": "OK"
          }
        }
      },
      "delete": {
        "tags": [
          "User"
        ],
        "parameters": [
          {
            "name": "userid",
            "in": "path",
            "required": true,
            "schema": {
              "type": "string"
            }
          },
          {
            "name": "fileName",
            "in": "path",
            "required": true,
            "schema": {
              "type": "string"
            }
          }
        ],
        "responses": {
          "200": {
            "description": "OK"
          }
        }
      }
    }
  },
  "components": {
    "schemas": {
      "CabinetDrugDto": {
        "type": "object",
        "properties": {
          "drugId": {
            "type": "string",
            "nullable": true
          },
          "note": {
            "type": "string",
            "nullable": true
          }
        },
        "additionalProperties": false
      },
      "CreateCabinetWithDrugsRequest": {
        "type": "object",
        "properties": {
          "cabinetName": {
            "type": "string",
            "nullable": true
          },
          "description": {
            "type": "string",
            "nullable": true
          },
          "drugList": {
            "type": "array",
            "items": {
              "$ref": "#/components/schemas/CabinetDrugDto"
            },
            "nullable": true
          }
        },
        "additionalProperties": false
      },
      "CreateReminderRequest": {
        "type": "object",
        "properties": {
          "note": {
            "type": "string",
            "nullable": true
          },
          "reminderTime": {
            "type": "string",
            "format": "time"
          },
          "repeatDays": {
            "type": "array",
            "items": {
              "type": "integer",
              "format": "int32"
            },
            "nullable": true
          },
          "drugIds": {
            "type": "array",
            "items": {
              "type": "string"
            },
            "nullable": true
          }
        },
        "additionalProperties": false
      },
      "DrugModelView": {
        "type": "object",
        "properties": {
          "drugId": {
            "type": "string",
            "nullable": true
          },
          "tenThuoc": {
            "type": "string",
            "nullable": true
          },
          "dotPheDuyet": {
            "type": "string",
            "nullable": true
          },
          "soQuyetDinh": {
            "type": "string",
            "nullable": true
          },
          "pheDuyet": {
            "type": "string",
            "format": "date",
            "nullable": true
          },
          "hieuLuc": {
            "type": "string",
            "nullable": true
          },
          "soDangKy": {
            "type": "string",
            "nullable": true
          },
          "hoatChat": {
            "type": "string",
            "nullable": true
          },
          "phanLoai": {
            "type": "string",
            "nullable": true
          },
          "nongDo": {
            "type": "string",
            "nullable": true
          },
          "taDuoc": {
            "type": "string",
            "nullable": true
          },
          "baoChe": {
            "type": "string",
            "nullable": true
          },
          "dongGoi": {
            "type": "string",
            "nullable": true
          },
          "tieuChuan": {
            "type": "string",
            "nullable": true
          },
          "tuoiTho": {
            "type": "string",
            "nullable": true
          },
          "congTySx": {
            "type": "string",
            "nullable": true
          },
          "congTySxCode": {
            "type": "string",
            "nullable": true
          },
          "nuocSx": {
            "type": "string",
            "nullable": true
          },
          "diaChiSx": {
            "type": "string",
            "nullable": true
          },
          "congTyDk": {
            "type": "string",
            "nullable": true
          },
          "nuocDk": {
            "type": "string",
            "nullable": true
          },
          "diaChiDk": {
            "type": "string",
            "nullable": true
          },
          "giaKeKhai": {
            "type": "number",
            "format": "double",
            "nullable": true
          },
          "huongDanSuDung": {
            "type": "string",
            "nullable": true
          },
          "huongDanSuDungBn": {
            "type": "string",
            "nullable": true
          },
          "nhomThuoc": {
            "type": "string",
            "nullable": true
          },
          "isHide": {
            "type": "boolean",
            "nullable": true
          },
          "rate": {
            "type": "number",
            "format": "double",
            "nullable": true
          },
          "rutSdk": {
            "type": "boolean",
            "nullable": true
          },
          "fileName": {
            "type": "string",
            "nullable": true
          },
          "state": {
            "type": "integer",
            "format": "int32",
            "nullable": true
          },
          "createdAt": {
            "type": "string",
            "format": "date-time",
            "nullable": true
          },
          "updatedAt": {
            "type": "string",
            "format": "date-time",
            "nullable": true
          },
          "images": {
            "type": "string",
            "nullable": true
          },
          "searchCount": {
            "type": "integer",
            "format": "int32",
            "nullable": true
          }
        },
        "additionalProperties": false
      },
      "ForgotPasswordModel": {
        "type": "object",
        "properties": {
          "email": {
            "type": "string",
            "nullable": true
          }
        },
        "additionalProperties": false
      },
      "LoginModelViews": {
        "required": [
          "email",
          "password"
        ],
        "type": "object",
        "properties": {
          "email": {
            "minLength": 1,
            "type": "string",
            "format": "email"
          },
          "password": {
            "minLength": 1,
            "type": "string"
          }
        },
        "additionalProperties": false
      },
      "LoginRequest": {
        "required": [
          "email",
          "password"
        ],
        "type": "object",
        "properties": {
          "email": {
            "type": "string",
            "nullable": true
          },
          "password": {
            "type": "string",
            "nullable": true
          },
          "twoFactorCode": {
            "type": "string",
            "nullable": true
          },
          "twoFactorRecoveryCode": {
            "type": "string",
            "nullable": true
          }
        },
        "additionalProperties": false
      },
      "RegisterModelViews": {
        "required": [
          "email",
          "name",
          "password",
          "phoneNumber"
        ],
        "type": "object",
        "properties": {
          "name": {
            "minLength": 1,
            "type": "string"
          },
          "email": {
            "minLength": 1,
            "type": "string",
            "format": "email"
          },
          "password": {
            "minLength": 6,
            "type": "string"
          },
          "phoneNumber": {
            "minLength": 1,
            "type": "string"
          },
          "roleId": {
            "type": "integer",
            "format": "int32"
          }
        },
        "additionalProperties": false
      },
      "ResetPasswordModel": {
        "type": "object",
        "properties": {
          "email": {
            "type": "string",
            "nullable": true
          },
          "newPassword": {
            "type": "string",
            "nullable": true
          },
          "confirmPassword": {
            "type": "string",
            "nullable": true
          },
          "otp": {
            "type": "string",
            "nullable": true
          }
        },
        "additionalProperties": false
      },
      "TokenRequest": {
        "type": "object",
        "properties": {
          "email": {
            "type": "string",
            "nullable": true
          },
          "refreshToken": {
            "type": "string",
            "nullable": true
          }
        },
        "additionalProperties": false
      },
      "TokenRqGoogleLogin": {
        "type": "object",
        "properties": {
          "idToken": {
            "type": "string",
            "nullable": true
          }
        },
        "additionalProperties": false
      },
      "UpdateDrugModelView": {
        "type": "object",
        "properties": {
          "tenThuoc": {
            "type": "string",
            "nullable": true
          },
          "hoatChat": {
            "type": "string",
            "nullable": true
          },
          "phanLoai": {
            "type": "string",
            "nullable": true
          },
          "nongDo": {
            "type": "string",
            "nullable": true
          },
          "taDuoc": {
            "type": "string",
            "nullable": true
          },
          "baoChe": {
            "type": "string",
            "nullable": true
          },
          "dongGoi": {
            "type": "string",
            "nullable": true
          },
          "tieuChuan": {
            "type": "string",
            "nullable": true
          },
          "tuoiTho": {
            "type": "string",
            "nullable": true
          },
          "congTySx": {
            "type": "string",
            "nullable": true
          },
          "congTySxCode": {
            "type": "string",
            "nullable": true
          },
          "nuocSx": {
            "type": "string",
            "nullable": true
          },
          "diaChiSx": {
            "type": "string",
            "nullable": true
          },
          "congTyDk": {
            "type": "string",
            "nullable": true
          },
          "nuocDk": {
            "type": "string",
            "nullable": true
          },
          "diaChiDk": {
            "type": "string",
            "nullable": true
          },
          "giaKeKhai": {
            "type": "number",
            "format": "double",
            "nullable": true
          },
          "huongDanSuDung": {
            "type": "string",
            "nullable": true
          },
          "huongDanSuDungBn": {
            "type": "string",
            "nullable": true
          },
          "nhomThuoc": {
            "type": "string",
            "nullable": true
          },
          "rate": {
            "type": "number",
            "format": "double",
            "nullable": true
          },
          "rutSdk": {
            "type": "boolean",
            "nullable": true
          },
          "fileName": {
            "type": "string",
            "nullable": true
          },
          "state": {
            "type": "integer",
            "format": "int32",
            "nullable": true
          },
          "images": {
            "type": "string",
            "nullable": true
          }
        },
        "additionalProperties": false
      },
      "UpdateReminderRequest": {
        "type": "object",
        "properties": {
          "note": {
            "type": "string",
            "nullable": true
          },
          "reminderTime": {
            "type": "string",
            "format": "time"
          },
          "repeatDays": {
            "type": "array",
            "items": {
              "type": "integer",
              "format": "int32"
            },
            "nullable": true
          },
          "drugIds": {
            "type": "array",
            "items": {
              "type": "string"
            },
            "nullable": true
          }
        },
        "additionalProperties": false
      },
      "UserCreateRequest": {
        "type": "object",
        "properties": {
          "name": {
            "type": "string",
            "nullable": true
          },
          "email": {
            "type": "string",
            "nullable": true
          },
          "password": {
            "type": "string",
            "nullable": true
          },
          "phoneNumber": {
            "type": "string",
            "nullable": true
          },
          "fcmtoken": {
            "type": "string",
            "nullable": true
          }
        },
        "additionalProperties": false
      },
      "UserUpdateRequest": {
        "type": "object",
        "properties": {
          "name": {
            "type": "string",
            "nullable": true
          },
          "phoneNumber": {
            "type": "string",
            "nullable": true
          },
          "fcmtoken": {
            "type": "string",
            "nullable": true
          }
        },
        "additionalProperties": false
      }
    },
    "securitySchemes": {
      "Bearer": {
        "type": "http",
        "description": "Enter 'Bearer' followed by a space and your JWT token.",
        "scheme": "Bearer",
        "bearerFormat": "JWT"
      }
    }
  },
  "security": [
    {
      "Bearer": [ ]
    }
  ]
}